{"id":6985,"identifier":"DVN/R9H1DC","persistentUrl":"https://doi.org/10.7939/DVN/R9H1DC","protocol":"doi","authority":"10.7939","publisher":"UAL Dataverse","publicationDate":"2017-06-16","storageIdentifier":"file://10.7939/DVN/R9H1DC","datasetVersion":{"id":1208,"datasetId":6985,"datasetPersistentId":"doi:10.7939/DVN/R9H1DC","storageIdentifier":"file://10.7939/DVN/R9H1DC","versionNumber":1,"versionMinorNumber":0,"versionState":"RELEASED","lastUpdateTime":"2017-06-16T20:59:38Z","releaseTime":"2017-06-16T20:59:38Z","createTime":"2017-06-16T19:41:00Z","license":"CC0","termsOfUse":"CC0 Waiver","fileAccessRequest":false,"metadataBlocks":{"citation":{"displayName":"Citation Metadata","fields":[{"typeName":"title","multiple":false,"typeClass":"primitive","value":"ANHA2 BES"},{"typeName":"author","multiple":true,"typeClass":"compound","value":[{"authorName":{"typeName":"authorName","multiple":false,"typeClass":"primitive","value":"X.H"},"authorAffiliation":{"typeName":"authorAffiliation","multiple":false,"typeClass":"primitive","value":"University of Alberta"}}]},{"typeName":"datasetContact","multiple":true,"typeClass":"compound","value":[{"datasetContactName":{"typeName":"datasetContactName","multiple":false,"typeClass":"primitive","value":"X.H"},"datasetContactAffiliation":{"typeName":"datasetContactAffiliation","multiple":false,"typeClass":"primitive","value":"University of Alberta"},"datasetContactEmail":{"typeName":"datasetContactEmail","multiple":false,"typeClass":"primitive","value":"xh@ualberta.ca"}}]},{"typeName":"dsDescription","multiple":true,"typeClass":"compound","value":[{"dsDescriptionValue":{"typeName":"dsDescriptionValue","multiple":false,"typeClass":"primitive","value":"some description about this run "}}]},{"typeName":"subject","multiple":true,"typeClass":"controlledVocabulary","value":["Earth and Environmental Sciences"]},{"typeName":"depositor","multiple":false,"typeClass":"primitive","value":"Davoodi, Danoosh"},{"typeName":"dateOfDeposit","multiple":false,"typeClass":"primitive","value":"2017-06-16"}]}},"files":[{"description":"The code in Python","label":"code_1.py","restricted":false,"version":1,"datasetVersionId":1208,"categories":["Code"],"dataFile":{"id":6988,"persistentId":"","pidURL":"","filename":"code_1.py","contentType":"text/x-python","filesize":0,"description":"The code in Python","storageIdentifier":"file://15cb2705b61-420a51f84532","rootDataFileId":-1,"md5":"d41d8cd98f00b204e9800998ecf8427e","checksum":{"type":"MD5","value":"d41d8cd98f00b204e9800998ecf8427e"},"creationDate":"2017-06-16"}},{"description":"System configurations","label":"system_setup_documentations.xml","restricted":false,"version":3,"datasetVersionId":1208,"categories":["Documentation"],"dataFile":{"id":6986,"persistentId":"","pidURL":"","filename":"system_setup_documentations.xml","contentType":"text/xml","filesize":31779,"description":"System configurations","storageIdentifier":"file://15cb26b059d-ae2168c0e9e2","rootDataFileId":-1,"md5":"6982aa9d31df7152b38bdb051103217f","checksum":{"type":"MD5","value":"6982aa9d31df7152b38bdb051103217f"},"creationDate":"2017-06-16"}}],"citation":"X.H, 2017, \"ANHA2 BES\", https://doi.org/10.7939/DVN/R9H1DC, UAL Dataverse, V1"}}