<?xml version="1.0" encoding="UTF-8"?>
<fits xmlns="http://hul.harvard.edu/ois/xml/ns/fits/fits_output" xmlns:xsi="http://www.w3.org/2001/XMLSchema-instance" xsi:schemaLocation="http://hul.harvard.edu/ois/xml/ns/fits/fits_output http://hul.harvard.edu/ois/xml/xsd/fits/fits_output.xsd" version="0.6.2" timestamp="10/12/15 11:31 AM">
  <identification>
    <identity format="Microsoft Word" mimetype="application/msword" toolname="FITS" toolversion="0.6.2">
      <tool toolname="file utility" toolversion="5.04"/>
      <tool toolname="Exiftool" toolversion="9.06"/>
      <tool toolname="NLNZ Metadata Extractor" toolversion="3.4GA"/>
      <tool toolname="ffident" toolversion="0.2"/>
    </identity>
  </identification>
  <fileinfo>
    <lastmodified toolname="Exiftool" toolversion="9.06" status="SINGLE_RESULT">2015:10:12 11:31:09-06:00</lastmodified>
    <created toolname="Exiftool" toolversion="9.06" status="CONFLICT">2014:07:16 21:31:00</created>
    <created toolname="NLNZ Metadata Extractor" toolversion="3.4GA" status="CONFLICT">2014-07-16 15:31:00</created>
    <creatingApplicationName toolname="Exiftool" toolversion="9.06">Microsoft Office Word</creatingApplicationName>
    <creatingApplicationVersion toolname="Exiftool" toolversion="9.06" status="CONFLICT">14.0000</creatingApplicationVersion>
    <creatingApplicationVersion toolname="NLNZ Metadata Extractor" toolversion="3.4GA" status="CONFLICT">0xc00f</creatingApplicationVersion>
    <filepath toolname="OIS File Information" toolversion="0.1" status="SINGLE_RESULT">/tmp/content-1.doc20151012-21156-7upxst.doc</filepath>
    <filename toolname="OIS File Information" toolversion="0.1" status="SINGLE_RESULT">CJASN_2011_6_6_Post-print.doc</filename>
    <size toolname="OIS File Information" toolversion="0.1" status="SINGLE_RESULT">163840</size>
    <md5checksum toolname="OIS File Information" toolversion="0.1" status="SINGLE_RESULT">0b21c5bf290740ac0dd993d712bfe36d</md5checksum>
    <fslastmodified toolname="OIS File Information" toolversion="0.1" status="SINGLE_RESULT">1444671069000</fslastmodified>
  </fileinfo>
  <filestatus/>
  <metadata>
    <document>
      <pageCount toolname="NLNZ Metadata Extractor" toolversion="3.4GA" status="SINGLE_RESULT">31</pageCount>
      <title toolname="Exiftool" toolversion="9.06">Testing a model of care for chronic kidney disease: the Can-Prevent clinical trial</title>
      <author toolname="Exiftool" toolversion="9.06">Brendan Barrett</author>
      <isRightsManaged toolname="Exiftool" toolversion="9.06" status="SINGLE_RESULT">no</isRightsManaged>
      <isProtected toolname="Exiftool" toolversion="9.06" status="SINGLE_RESULT">no</isProtected>
      <wordCount toolname="NLNZ Metadata Extractor" toolversion="3.4GA" status="SINGLE_RESULT">5624</wordCount>
      <characterCount toolname="NLNZ Metadata Extractor" toolversion="3.4GA" status="SINGLE_RESULT">32061</characterCount>
      <language toolname="NLNZ Metadata Extractor" toolversion="3.4GA" status="SINGLE_RESULT">U.S. English</language>
    </document>
  </metadata>
</fits>