<?xml version="1.0" encoding="UTF-8"?>
<record xmlns="http://www.loc.gov/MARC21/slim">
  <leader>02119nam a2200409 a 4500</leader>
  <controlfield tag="001">3180281</controlfield>
  <controlfield tag="007">he amb---bbcp</controlfield>
  <controlfield tag="007">he bmb---baap</controlfield>
  <controlfield tag="008">860707s1715    ne      b     000 0 fre d</controlfield>
  <datafield tag="020" ind1=" " ind2=" ">
    <subfield code="a">0665422547</subfield>
  </datafield>
  <datafield tag="035" ind1=" " ind2=" ">
    <subfield code="a">ocm62904377</subfield>
  </datafield>
  <datafield tag="040" ind1=" " ind2=" ">
    <subfield code="a">CaOOCIHM</subfield>
    <subfield code="b">fre</subfield>
    <subfield code="c">CaOOCIHM</subfield>
    <subfield code="d">AEU</subfield>
  </datafield>
  <datafield tag="043" ind1=" " ind2=" ">
    <subfield code="a">e-uk---</subfield>
  </datafield>
  <datafield tag="082" ind1="0" ind2=" ">
    <subfield code="a">940.2/526</subfield>
    <subfield code="2">19</subfield>
  </datafield>
  <datafield tag="090" ind1=" " ind2=" ">
    <subfield code="a">FC 02 0203 no. 42254</subfield>
    <subfield code="b">AEU</subfield>
  </datafield>
  <datafield tag="245" ind1="0" ind2="0">
    <subfield code="a">Rapport du comitté secret nommé par la Chambre basse du Parlement de la Grande-Bretagne</subfield>
    <subfield code="h">[microforme] :</subfield>
    <subfield code="b">pour faire l&apos;examen des livres &amp; papiers qui roulent sur les negotiations de la derniere paix &amp; du traité de commerce &amp;c. : fait le 9. juin V.S. 1715 /</subfield>
    <subfield code="c">par le sieur Robert Walpole, president du committé ; avec tous les memoires, lettres secretes &amp; autres papiers transigés entre les ministres d&apos;Angleterre &amp; ceux de France.</subfield>
  </datafield>
  <datafield tag="260" ind1=" " ind2=" ">
    <subfield code="a">A Amsterdam :</subfield>
    <subfield code="b">Chez les freres Wetstein,</subfield>
    <subfield code="c">1715.</subfield>
  </datafield>
  <datafield tag="300" ind1=" " ind2=" ">
    <subfield code="a">6 microfiches (263 images).</subfield>
  </datafield>
  <datafield tag="490" ind1="1" ind2=" ">
    <subfield code="a">CIHM/ICMH Microfiche series = CIHM/ICMH collection de microfiches ;</subfield>
    <subfield code="v">no. 42254</subfield>
  </datafield>
  <datafield tag="500" ind1=" " ind2=" ">
    <subfield code="a">&quot;Imprimé par Ordre du Parlement.&quot;</subfield>
  </datafield>
  <datafield tag="500" ind1=" " ind2=" ">
    <subfield code="a">&quot;Premiere partie.&quot;</subfield>
  </datafield>
  <datafield tag="500" ind1=" " ind2=" ">
    <subfield code="a">&quot;Traduit de l&apos;Anglois.&quot;</subfield>
  </datafield>
  <datafield tag="533" ind1=" " ind2=" ">
    <subfield code="a">Microfiche de l&apos;exemplaire de l&apos;édition originale se trouvant à la Douglas Library, Queen&apos;s University.</subfield>
    <subfield code="b">Ottawa :</subfield>
    <subfield code="c">Institut canadien de microreproductions historiques,</subfield>
    <subfield code="d">1985.</subfield>
  </datafield>
  <datafield tag="534" ind1=" " ind2=" ">
    <subfield code="e">[3], 40, 456 p. ; 13 cm.</subfield>
  </datafield>
  <datafield tag="596" ind1=" " ind2=" ">
    <subfield code="a">43</subfield>
  </datafield>
  <datafield tag="630" ind1="0" ind2="6">
    <subfield code="a">Traité d&apos;Utrecht</subfield>
    <subfield code="d">(1713).</subfield>
  </datafield>
  <datafield tag="630" ind1="0" ind2="0">
    <subfield code="a">Treaty of Utrecht</subfield>
    <subfield code="d">(1713).</subfield>
  </datafield>
  <datafield tag="650" ind1=" " ind2="6">
    <subfield code="a">Guerre de la Succession d&apos;Espagne, 1701-1714</subfield>
    <subfield code="x">Sources.</subfield>
  </datafield>
  <datafield tag="650" ind1=" " ind2="0">
    <subfield code="a">Spanish Succession, War of, 1701-1714</subfield>
    <subfield code="x">Sources.</subfield>
  </datafield>
  <datafield tag="651" ind1=" " ind2="6">
    <subfield code="a">Grande-Bretagne</subfield>
    <subfield code="x">Relations extérieures</subfield>
    <subfield code="y">1702-1714.</subfield>
  </datafield>
  <datafield tag="651" ind1=" " ind2="0">
    <subfield code="a">Great Britain</subfield>
    <subfield code="x">Foreign relations</subfield>
    <subfield code="y">1702-1714.</subfield>
  </datafield>
  <datafield tag="700" ind1="1" ind2=" ">
    <subfield code="a">Walpole, Robert,</subfield>
    <subfield code="c">Earl of Orford,</subfield>
    <subfield code="d">1676-1745.</subfield>
  </datafield>
  <datafield tag="710" ind1="1" ind2=" ">
    <subfield code="a">Grande-Bretagne.</subfield>
    <subfield code="b">Parliament.</subfield>
    <subfield code="b">House of Commons.</subfield>
    <subfield code="b">Committee of Secrecy Relating to the Negociations of Peace and Commerce.</subfield>
  </datafield>
  <datafield tag="830" ind1=" " ind2="0">
    <subfield code="a">CIHM/ICMH microfiche series ;</subfield>
    <subfield code="v">no. 42254</subfield>
  </datafield>
  <datafield tag="949" ind1=" " ind2=" ">
    <subfield code="h">UAHS-MF</subfield>
    <subfield code="z">CIHMMPRE</subfield>
  </datafield>
  <datafield tag="016" ind1=" " ind2=" ">
    <subfield code="a"> 866035672</subfield>
  </datafield>
  <datafield tag="926" ind1=" " ind2=" ">
    <subfield code="a">UAHSS</subfield>
    <subfield code="b">MICROFICHE</subfield>
    <subfield code="c">FC 02 0203 no. 42254</subfield>
    <subfield code="d">MICROFORM</subfield>
    <subfield code="f">1</subfield>
  </datafield>
</record>
