<?xml version="1.0" encoding="UTF-8"?><rdf:RDF xmlns:oai="http://www.openarchives.org/OAI/2.0/" xmlns:rdf="http://www.w3.org/1999/02/22-rdf-syntax-ns#" xmlns:dc="http://purl.org/dc/elements/1.1/" xmlns:ual="http://terms.library.ualberta.ca/" xmlns:bibo="http://purl.org/ontology/bibo/" xmlns:dcterms="http://purl.org/dc/terms/" xmlns:schema="https://schema.org/" xmlns:etdms="http://www.ndltd.org/standards/metadata/etdms/1.0/" xmlns:xsi="http://www.w3.org/2001/XMLSchema-instance"><rdf:Description rdf:about="http://example.org/oai%3Aescholarship.mcgill.ca%3Apc289j92b"><ual:graduationDate>1970</ual:graduationDate><dcterms:language>eng</dcterms:language><schema:inSupportOf>Doctor of Philosophy</schema:inSupportOf><dc:contributor>Department of Chemistry</dc:contributor><dcterms:publisher rdf:resource="http://dbpedia.org/resource/McGill_University"/><dcterms:title>The solid state polymerization of hydrated calcium acrylate and hydrated barium methacrylate</dcterms:title><ual:dissertant>Costaschuk, Fred Michael</ual:dissertant><dc:identifier>https://escholarship.mcgill.ca/downloads/h415pb30t.pdf</dc:identifier><ual:fedora3Handle>https://escholarship.mcgill.ca/concern/theses/pc289j92b</ual:fedora3Handle><dc:subject>Acrylates</dc:subject><dc:subject>Polymers</dc:subject><dc:subject>Methyl methacrylate</dc:subject><dc:subject>Polymers -- Effect of radiation on</dc:subject></rdf:Description><rdf:Description rdf:about="http://example.org/oai%3Aescholarship.mcgill.ca%3A0v838148q"><ual:graduationDate>1970</ual:graduationDate><dcterms:language>eng</dcterms:language><schema:inSupportOf>Doctor of Philosophy</schema:inSupportOf><dc:contributor>Department of Psychology</dc:contributor><dcterms:publisher rdf:resource="http://dbpedia.org/resource/McGill_University"/><dcterms:title>Psychophysiological concomitants of attention in hyperactive children</dcterms:title><ual:dissertant>Cohen, Nancy J.</ual:dissertant><dc:identifier>https://escholarship.mcgill.ca/downloads/z029p555g.pdf</dc:identifier><ual:fedora3Handle>https://escholarship.mcgill.ca/concern/theses/0v838148q</ual:fedora3Handle><dc:subject>Child psychology</dc:subject><dc:subject>Problem children</dc:subject></rdf:Description><rdf:Description rdf:about="http://example.org/oai%3Aescholarship.mcgill.ca%3As4655h55x"><ual:graduationDate>1970</ual:graduationDate><dcterms:language>eng</dcterms:language><schema:inSupportOf>Doctor of Philosophy</schema:inSupportOf><dc:contributor>Department of Chemistry</dc:contributor><dcterms:publisher rdf:resource="http://dbpedia.org/resource/McGill_University"/><dcterms:title>Aspects of the chemistry of compounds containing (PNP), (PNS) and (SNS)</dcterms:title><ual:dissertant>Clipsham, Ruth Marian</ual:dissertant><dc:identifier>https://escholarship.mcgill.ca/downloads/xd07gt54d.pdf</dc:identifier><ual:fedora3Handle>https://escholarship.mcgill.ca/concern/theses/s4655h55x</ual:fedora3Handle><dc:subject>Phosphorus compounds</dc:subject><dc:subject>Nitriles</dc:subject><dc:subject>Sulfur compounds</dc:subject></rdf:Description><rdf:Description rdf:about="http://example.org/oai%3Aescholarship.mcgill.ca%3Ak0698838d"><ual:graduationDate>1970</ual:graduationDate><dcterms:language>eng</dcterms:language><schema:inSupportOf>Doctor of Philosophy</schema:inSupportOf><dc:contributor>Department of Mechanical Engineering</dc:contributor><dcterms:publisher rdf:resource="http://dbpedia.org/resource/McGill_University"/><dcterms:title>Self-preserving two-dimensional jets in streaming flow</dcterms:title><ual:dissertant>Fekete, George Ivan</ual:dissertant><dc:identifier>https://escholarship.mcgill.ca/downloads/2514nm36f.pdf</dc:identifier><ual:fedora3Handle>https://escholarship.mcgill.ca/concern/theses/k0698838d</ual:fedora3Handle><dc:subject>Jets -- Fluid dynamics</dc:subject></rdf:Description><rdf:Description rdf:about="http://example.org/oai%3Aescholarship.mcgill.ca%3Aqr46r189w"><ual:graduationDate>1969</ual:graduationDate><dcterms:language>eng</dcterms:language><schema:inSupportOf>Doctor of Philosophy</schema:inSupportOf><dc:contributor>Department of Civil Engineering and Applied Mechanics</dc:contributor><dcterms:publisher rdf:resource="http://dbpedia.org/resource/McGill_University"/><dcterms:title>Matrix analysis of welded tubular joints</dcterms:title><ual:dissertant>Mehrotra, Bharat Lal</ual:dissertant><dc:identifier>https://escholarship.mcgill.ca/downloads/qr46r190n.pdf</dc:identifier><ual:fedora3Handle>https://escholarship.mcgill.ca/concern/theses/qr46r189w</ual:fedora3Handle><dc:subject>Structural analysis (Engineering)</dc:subject></rdf:Description><rdf:Description rdf:about="http://example.org/oai%3Aescholarship.mcgill.ca%3Avx021g11k"><ual:graduationDate>1970</ual:graduationDate><dcterms:language>eng</dcterms:language><schema:inSupportOf>Doctor of Philosophy</schema:inSupportOf><dc:contributor>Department of Chemistry</dc:contributor><dcterms:publisher rdf:resource="http://dbpedia.org/resource/McGill_University"/><dcterms:title>Studies in nuclear magnetic resonance</dcterms:title><ual:dissertant>Matthews, Christopher Howard</ual:dissertant><dc:identifier>https://escholarship.mcgill.ca/downloads/1n79h531x.pdf</dc:identifier><ual:fedora3Handle>https://escholarship.mcgill.ca/concern/theses/vx021g11k</ual:fedora3Handle><dc:subject>Nuclear magnetic resonance</dc:subject><dc:subject>Pyridine</dc:subject></rdf:Description><rdf:Description rdf:about="http://example.org/oai%3Aescholarship.mcgill.ca%3A7h149q722"><ual:graduationDate>1969</ual:graduationDate><dcterms:language>eng</dcterms:language><schema:inSupportOf>Doctor of Philosophy</schema:inSupportOf><dc:contributor>Department of Chemistry</dc:contributor><dcterms:publisher rdf:resource="http://dbpedia.org/resource/McGill_University"/><dcterms:title>The irradiation chemistry of methylsiloxanes adsorbed on silica</dcterms:title><ual:dissertant>Maeng, Ki-Suck</ual:dissertant><dc:identifier>https://escholarship.mcgill.ca/downloads/w95051402.pdf</dc:identifier><ual:fedora3Handle>https://escholarship.mcgill.ca/concern/theses/7h149q722</ual:fedora3Handle><dc:subject>Siloxanes</dc:subject><dc:subject>Silica</dc:subject><dc:subject>Radiochemistry</dc:subject></rdf:Description><rdf:Description rdf:about="http://example.org/oai%3Aescholarship.mcgill.ca%3Aw6634466z"><ual:graduationDate>1970</ual:graduationDate><dcterms:language>eng</dcterms:language><schema:inSupportOf>Doctor of Philosophy</schema:inSupportOf><dc:contributor>Department of French Language and Literature</dc:contributor><dcterms:publisher rdf:resource="http://dbpedia.org/resource/McGill_University"/><dcterms:title>The novels of Pigault-Lebrun</dcterms:title><ual:dissertant>Ludlow, Gregory</ual:dissertant><dc:identifier>https://escholarship.mcgill.ca/downloads/hm50ts49m.pdf</dc:identifier><ual:fedora3Handle>https://escholarship.mcgill.ca/concern/theses/w6634466z</ual:fedora3Handle><dc:subject>Pigault-Lebrun, 1753-1835</dc:subject></rdf:Description><rdf:Description rdf:about="http://example.org/oai%3Aescholarship.mcgill.ca%3Ac247dt00x"><ual:graduationDate>1969</ual:graduationDate><dcterms:language>eng</dcterms:language><schema:inSupportOf>Doctor of Philosophy</schema:inSupportOf><dc:contributor>Department of Chemistry</dc:contributor><dcterms:publisher rdf:resource="http://dbpedia.org/resource/McGill_University"/><dcterms:title>Studies in nuclear magnetic resonance : I. Anisotropy of the fluorine shielding constants in substituted fluorobenzenes. II. Molecular motions in borane and borontrihalide complexes</dcterms:title><ual:dissertant>Yim, Chung-Tat</ual:dissertant><dc:identifier>https://escholarship.mcgill.ca/downloads/mg74qm872.pdf</dc:identifier><ual:fedora3Handle>https://escholarship.mcgill.ca/concern/theses/c247dt00x</ual:fedora3Handle><dc:subject>Nuclear magnetic resonance</dc:subject></rdf:Description><rdf:Description rdf:about="http://example.org/oai%3Aescholarship.mcgill.ca%3A3t945r70b"><ual:graduationDate>1969</ual:graduationDate><dcterms:language>eng</dcterms:language><schema:inSupportOf>Doctor of Philosophy</schema:inSupportOf><dc:contributor>Marine Sciences Centre</dc:contributor><dcterms:publisher rdf:resource="http://dbpedia.org/resource/McGill_University"/><dcterms:title>The relation between production and standing crop of phytoplankton : a study in St. Margaret's Bay, N.S.</dcterms:title><ual:dissertant>Saifullah, Syed Mohammed</ual:dissertant><dc:identifier>https://escholarship.mcgill.ca/downloads/dr26xz17k.pdf</dc:identifier><ual:fedora3Handle>https://escholarship.mcgill.ca/concern/theses/3t945r70b</ual:fedora3Handle><dc:subject>Phytoplankton -- St. Margaret's Bay (N.S.)</dc:subject></rdf:Description><rdf:Description rdf:about="http://example.org/oai%3Aescholarship.mcgill.ca%3A9s161714s"><ual:graduationDate>1969</ual:graduationDate><dcterms:language>eng</dcterms:language><schema:inSupportOf>Doctor of Philosophy</schema:inSupportOf><dc:contributor>Department of Anthropology</dc:contributor><dcterms:publisher rdf:resource="http://dbpedia.org/resource/McGill_University"/><dcterms:title>Conflict and cohesion in an East Pakistani village</dcterms:title><ual:dissertant>Islam, A. K. M. Aminul</ual:dissertant><dc:identifier>https://escholarship.mcgill.ca/downloads/pg15bf919.pdf</dc:identifier><ual:fedora3Handle>https://escholarship.mcgill.ca/concern/theses/9s161714s</ual:fedora3Handle><dc:subject>Social change</dc:subject><dc:subject>Masarchar, Bangladesh -- Politics and government</dc:subject></rdf:Description><rdf:Description rdf:about="http://example.org/oai%3Aescholarship.mcgill.ca%3Afq977v85g"><ual:graduationDate>1969</ual:graduationDate><dcterms:language>eng</dcterms:language><schema:inSupportOf>Doctor of Philosophy</schema:inSupportOf><dc:contributor>Department of Mathematics</dc:contributor><dcterms:publisher rdf:resource="http://dbpedia.org/resource/McGill_University"/><dcterms:title>Certain properties of lX-X for [sigma] compact X</dcterms:title><ual:dissertant>Woods, R. Grant</ual:dissertant><dc:identifier>https://escholarship.mcgill.ca/downloads/kp78gh27q.pdf</dc:identifier><ual:fedora3Handle>https://escholarship.mcgill.ca/concern/theses/fq977v85g</ual:fedora3Handle><dc:subject>Topology</dc:subject></rdf:Description><rdf:Description rdf:about="http://example.org/oai%3Aescholarship.mcgill.ca%3Avd66w080j"><ual:graduationDate>1968</ual:graduationDate><dcterms:language>eng</dcterms:language><schema:inSupportOf>Doctor of Philosophy</schema:inSupportOf><dc:contributor>Department of Chemistry</dc:contributor><dcterms:publisher rdf:resource="http://dbpedia.org/resource/McGill_University"/><dcterms:title>The effect of interfacial energetics on the physical properties of silica-polydimethyl siloxane composites</dcterms:title><ual:dissertant>Chahal, Ramlal Singh</ual:dissertant><dc:identifier>https://escholarship.mcgill.ca/downloads/fb494942v.pdf</dc:identifier><ual:fedora3Handle>https://escholarship.mcgill.ca/concern/theses/vd66w080j</ual:fedora3Handle><dc:subject>Polymers -- Effect of radiation on</dc:subject></rdf:Description><rdf:Description rdf:about="http://example.org/oai%3Aescholarship.mcgill.ca%3A8w32r659c"><ual:graduationDate>1968</ual:graduationDate><dcterms:language>eng</dcterms:language><schema:inSupportOf>Doctor of Philosophy</schema:inSupportOf><dc:contributor>Department of Agricultural Chemistry</dc:contributor><dcterms:publisher rdf:resource="http://dbpedia.org/resource/McGill_University"/><dcterms:title>The in vivo conversion products of parenterally administered progesterone in the hen</dcterms:title><ual:dissertant>Chen, Percival Henry</ual:dissertant><dc:identifier>https://escholarship.mcgill.ca/downloads/x059c8431.pdf</dc:identifier><ual:fedora3Handle>https://escholarship.mcgill.ca/concern/theses/8w32r659c</ual:fedora3Handle><dc:subject>Poultry -- Physiology</dc:subject><dc:subject>Progesterone</dc:subject></rdf:Description><rdf:Description rdf:about="http://example.org/oai%3Aescholarship.mcgill.ca%3Awd375x20x"><ual:graduationDate>1969</ual:graduationDate><dcterms:language>eng</dcterms:language><schema:inSupportOf>Doctor of Philosophy</schema:inSupportOf><dc:contributor>Department of Soil Science</dc:contributor><dcterms:publisher rdf:resource="http://dbpedia.org/resource/McGill_University"/><dcterms:title>Effects of light intensity and nitrogen on growth of corn and grass-legume mixture</dcterms:title><ual:dissertant>Chan, Wing-To.</ual:dissertant><dc:identifier>https://escholarship.mcgill.ca/downloads/bn999759h.pdf</dc:identifier><ual:fedora3Handle>https://escholarship.mcgill.ca/concern/theses/wd375x20x</ual:fedora3Handle><dc:subject>Nitrogen fertilizers</dc:subject><dc:subject>Light -- Physiological effect</dc:subject></rdf:Description><rdf:Description rdf:about="http://example.org/oai%3Aescholarship.mcgill.ca%3A1831ck88k"><ual:graduationDate>1969</ual:graduationDate><dcterms:language>eng</dcterms:language><schema:inSupportOf>Doctor of Philosophy</schema:inSupportOf><dc:contributor>Department of Chemistry</dc:contributor><dcterms:publisher rdf:resource="http://dbpedia.org/resource/McGill_University"/><dcterms:title>Isotopic exchange reactions in unimolecular films</dcterms:title><ual:dissertant>Cooke, William Reginald Ford</ual:dissertant><dc:identifier>https://escholarship.mcgill.ca/downloads/2v23vv20c.pdf</dc:identifier><ual:fedora3Handle>https://escholarship.mcgill.ca/concern/theses/1831ck88k</ual:fedora3Handle><dc:subject>Film coefficients (Physics)</dc:subject><dc:subject>Fatty acids</dc:subject></rdf:Description><rdf:Description rdf:about="http://example.org/oai%3Aescholarship.mcgill.ca%3Akk91fm500"><ual:graduationDate>1968</ual:graduationDate><dcterms:language>eng</dcterms:language><schema:inSupportOf>Doctor of Philosophy</schema:inSupportOf><dc:contributor>Department of Entomology</dc:contributor><dcterms:publisher rdf:resource="http://dbpedia.org/resource/McGill_University"/><dcterms:title>The Mesostigmata of certain coniferous forest soils western Quebec, with a preliminary account of the North American Rhodacaridae (Acarina)</dcterms:title><ual:dissertant>Emberson, Rowan Mark</ual:dissertant><dc:identifier>https://escholarship.mcgill.ca/downloads/jw827c636.pdf</dc:identifier><ual:fedora3Handle>https://escholarship.mcgill.ca/concern/theses/kk91fm500</ual:fedora3Handle><dc:subject>Mites</dc:subject><dc:subject>Rhodacaridae</dc:subject><dc:subject>Mites -- Québec (Province)</dc:subject></rdf:Description><rdf:Description rdf:about="http://example.org/oai%3Aescholarship.mcgill.ca%3A5138jf666"><ual:graduationDate>1968</ual:graduationDate><dcterms:language>eng</dcterms:language><schema:inSupportOf>Doctor of Philosophy</schema:inSupportOf><dc:contributor>Department of Philosophy</dc:contributor><dcterms:publisher rdf:resource="http://dbpedia.org/resource/McGill_University"/><dcterms:title>Reference and intensionality : an essay on Quine's philosophy of logic</dcterms:title><ual:dissertant>Egyed, Bela Imre</ual:dissertant><dc:identifier>https://escholarship.mcgill.ca/downloads/4j03d0648.pdf</dc:identifier><ual:fedora3Handle>https://escholarship.mcgill.ca/concern/theses/5138jf666</ual:fedora3Handle><dc:subject>Quine, W. V. (Willard Van Orman)</dc:subject><dc:subject>Modality (Logic)</dc:subject></rdf:Description><rdf:Description rdf:about="http://example.org/oai%3Aescholarship.mcgill.ca%3A79407z15w"><ual:graduationDate>1968</ual:graduationDate><dcterms:language>eng</dcterms:language><schema:inSupportOf>Doctor of Philosophy</schema:inSupportOf><dc:contributor>Department of Botany</dc:contributor><dcterms:publisher rdf:resource="http://dbpedia.org/resource/McGill_University"/><dcterms:title>Development of glycoside hydrolase and pectic enzyme activities in growing pea epicotyl tissue</dcterms:title><ual:dissertant>Datko, Anne Harmon</ual:dissertant><dc:identifier>https://escholarship.mcgill.ca/downloads/vq27zp284.pdf</dc:identifier><ual:fedora3Handle>https://escholarship.mcgill.ca/concern/theses/79407z15w</ual:fedora3Handle><dc:subject>Growth (Plants)</dc:subject><dc:subject>Peas</dc:subject><dc:subject>Morphogenesis</dc:subject><dc:subject>Enzymes</dc:subject></rdf:Description><rdf:Description rdf:about="http://example.org/oai%3Aescholarship.mcgill.ca%3A8336h280j"><ual:graduationDate>1968</ual:graduationDate><dcterms:language>eng</dcterms:language><schema:inSupportOf>Doctor of Philosophy</schema:inSupportOf><dc:contributor>Department of Botany</dc:contributor><dcterms:publisher rdf:resource="http://dbpedia.org/resource/McGill_University"/><dcterms:title>Formation of cellulase activity by pea microsomes both in vivo and in vitro</dcterms:title><ual:dissertant>Davies, Eric H.</ual:dissertant><dc:identifier>https://escholarship.mcgill.ca/downloads/xs55mc844.pdf</dc:identifier><ual:fedora3Handle>https://escholarship.mcgill.ca/concern/theses/8336h280j</ual:fedora3Handle><dc:subject>Cellulase</dc:subject><dc:subject>Peas</dc:subject><dc:subject>Growth factors</dc:subject></rdf:Description><rdf:Description rdf:about="http://example.org/oai%3Aescholarship.mcgill.ca%3A5712m750s"><ual:graduationDate>1993</ual:graduationDate><dcterms:language>spa</dcterms:language><schema:inSupportOf>Master of Arts</schema:inSupportOf><dc:contributor>Department of Hispanic Studies</dc:contributor><dcterms:publisher rdf:resource="http://dbpedia.org/resource/McGill_University"/><dcterms:title>Opresión y búsqueda de la identidad de la mujer (Esther Tusquets en la novela posfranquista)</dcterms:title><ual:dissertant>Odartey-Wellington, Dorothy</ual:dissertant><dc:abstract>The thesis is focused on the first three novels of Esther Tusquets: El mismo mar de todos los veranos (1978), El amor es un juego solitario (1979) and Varada tras el ultimo naufragio (1980). It is inspired by the central theme of the three novels--the Spanish middle-class woman's search for identity--and it aims at showing that the female protagonists' search for identity and their failure in the process is inextricably linked with General Franco's dictatorial policy of imposing traditional norms and values on the Spanish people between 1939-1975. The introduction summarizes the novels, explains the objectives of the thesis and looks at some critique of Tusquets' novels. Chapter one provides the socio-historical setting of the novels. It highlights details of the Civil Code and Francoist law and propaganda and their influence on women's identity and male/female relations. Chapter two analyses the depersonalized condition of the protagonists and the third chapter takes a look at an attempt to redeem the women's identity. Chapter four examines the protagonists' failure and it is followed by a brief section of conclusions.</dc:abstract><ual:supervisor>Magallon, Jesus Perez</ual:supervisor><dc:identifier>https://escholarship.mcgill.ca/downloads/zc77sr06k.pdf</dc:identifier><ual:fedora3Handle>https://escholarship.mcgill.ca/concern/theses/5712m750s</ual:fedora3Handle><dc:subject>Women in literature</dc:subject><dc:subject>Tusquets, Esther -- Criticism and interpretation</dc:subject><dc:subject>Tusquets, Esther -- Characters -- Women</dc:subject></rdf:Description><rdf:Description rdf:about="http://example.org/oai%3Aescholarship.mcgill.ca%3A2227mq73b"><ual:graduationDate>1993</ual:graduationDate><dcterms:language>rus</dcterms:language><schema:inSupportOf>Master of Arts</schema:inSupportOf><dc:contributor>Department of Russian and Slavic Studies</dc:contributor><dcterms:publisher rdf:resource="http://dbpedia.org/resource/McGill_University"/><dcterms:title>Comparative analysis of the Christian theme in Soviet literature</dcterms:title><ual:dissertant>Prager, Valerie</ual:dissertant><dc:abstract>During the 70 years of the Soviet regime the officially approved Soviet literature consistently reflected an exclusively materialistic world view. As a result, there were very few critical works, published in the West, dealing with the Christian theme in Russian literature of the Soviet period. Surprisingly, literature with the Christian theme did exist in the years of militant state atheism. Such literary works raised questions about the purpose of life, about truth, moral courage and the person of Christ. These books were published during the 60-s, the time of the "thaw", and became a focal point of public discussions. Two of them--Bulgakov's "Master i Margarita" and Pasternak's "Doktor Zhivago" were internationally acknowledged as major literary works. This study will examine in detail and compare five literary works with christian content, published in the Soviet years of Russia. Two of them were mentioned above. The other three are "Plakha" by Aytmatov, "Dzhvari" by Alfeeva and "Fakul'tet nenizhnikh veshchei" by Dombrovsky. The existence of such literature proves that all the efforts to suppress the human spirit and its longing for the Absolute have failed.</dc:abstract><ual:supervisor>Patera, T.</ual:supervisor><dc:identifier>https://escholarship.mcgill.ca/downloads/6969z1737.pdf</dc:identifier><ual:fedora3Handle>https://escholarship.mcgill.ca/concern/theses/2227mq73b</ual:fedora3Handle><dc:subject>Russian literature -- 20th century -- History and criticism</dc:subject><dc:subject>Christianity in literature</dc:subject></rdf:Description><rdf:Description rdf:about="http://example.org/oai%3Aescholarship.mcgill.ca%3A3t945r71m"><ual:graduationDate>1993</ual:graduationDate><dcterms:language>eng</dcterms:language><schema:inSupportOf>Master of Arts</schema:inSupportOf><dc:contributor>Department of Philosophy</dc:contributor><dcterms:publisher rdf:resource="http://dbpedia.org/resource/McGill_University"/><dcterms:title>The limits of authority and property, or, How not to argue for anarchism</dcterms:title><ual:dissertant>Pates, Rebecca</ual:dissertant><dc:abstract>Anarchist theory assumes that non-hierarchically organised societies both possible and desirable. To show the former requires (1) empirical evidence and (2) a discussion of the theoretical preconditions of cooperation. To show the latter, it is necessary to show that the faults found with the state can be remedied within non-hierarchically ordered societies. One obvious condition for a successful anarchist theory is that the solutions to these separate tasks are mutually consistent. It is the aim of this thesis to show that the theories of Robert Paul Wolff and Robert Nozick are found wanting in this respect. Both their theories of agency rule out the possibility of non-coercive and stable cooperation, which is a necessary precondition for an anarchist society. I conclude with a brief discussion of Michael Taylor's communitarian proposal and defend it against the liberal.</dc:abstract><ual:supervisor>Dwyer, S.</ual:supervisor><dc:identifier>https://escholarship.mcgill.ca/downloads/4m90dw453.pdf</dc:identifier><ual:fedora3Handle>https://escholarship.mcgill.ca/concern/theses/3t945r71m</ual:fedora3Handle><dc:subject>Authority -- Philosophy</dc:subject><dc:subject>Property -- Philosophy</dc:subject><dc:subject>Anarchism -- Philosophy</dc:subject></rdf:Description><rdf:Description rdf:about="http://example.org/oai%3Aescholarship.mcgill.ca%3Ahm50ts50c"><ual:graduationDate>1993</ual:graduationDate><dcterms:language>eng</dcterms:language><schema:inSupportOf>Master of Arts</schema:inSupportOf><dc:contributor>Department of History</dc:contributor><dcterms:publisher rdf:resource="http://dbpedia.org/resource/McGill_University"/><dcterms:title>The feminization of the Crown : the role of a Governor-General's consort in post-Confederation Canada, 1867-1898</dcterms:title><ual:dissertant>Philogène, Simone</ual:dissertant><dc:abstract>In Walter Bagehot's book, The English Constitution (1867), he described the role that the Crown was to play in the late Victorian Age. Separating the Constitution into two parts, the dignified and the efficient, he deemed the Crown part of the dignified part of the Constitution. The roles he assigned to this dignified Crown, were by nineteenth century standards, "feminine"--symbol of virtue, societal leader and personification of family life. In Canada, this feminization of the Crown was particularly evident from 1872 onwards. With the arrival of Harriot, Lady Dufferin, Consort to Canada's third Governor-General, Lord Dufferin, the functions of the Crown in Canada became increasingly feminine activities. Lady Dufferin's successors extended the feminization of the Crown.</dc:abstract><ual:supervisor>Miller, Carman</ual:supervisor><dc:identifier>https://escholarship.mcgill.ca/downloads/4f16c3641.pdf</dc:identifier><ual:fedora3Handle>https://escholarship.mcgill.ca/concern/theses/hm50ts50c</ual:fedora3Handle><dc:subject>Governors general -- Canada</dc:subject><dc:subject>Spouses -- Canada</dc:subject></rdf:Description><rdf:Description rdf:about="http://example.org/oai%3Aescholarship.mcgill.ca%3Anz806066j"><ual:graduationDate>1985</ual:graduationDate><dcterms:language>eng</dcterms:language><schema:inSupportOf>Doctor of Philosophy</schema:inSupportOf><dc:contributor>Department of History</dc:contributor><dcterms:publisher rdf:resource="http://dbpedia.org/resource/McGill_University"/><dcterms:title>The Office du Niger under colonial rule : its origin, evolution, and character, 1920-1960</dcterms:title><ual:dissertant>Filipovich, Jean, 1947-</ual:dissertant><dc:abstract>Le projet d'irrigation de l'Office du Niger, situé dans le delta intérieur du Niger au Mali, est né d'une proposition très insuffisante mais grandiose conçue en 1920 par un ingénieur des Travaux Publics Coloniaux, Émile Bélime. Conçu à l'origine comme un moyen de transformer la Vallée du Niger en une vaste plantation de coton, et envisagé par la suite comme le grenier central de l'Afrique Occidentale, ce projet n'a jamais atteint qu'une petite partie de son potentiel agricole espéré. Sa réalisation et sa mise en exploitation on nécessité le déracinement par contrainte de dizaines de milliers d'Africains. Même après la deuxième guerre mondiale, le projet a absorbé encore une grande partie des revenus coloniaux, déjà limités, mais il n'a généré aucun revenu.  Pendant l'entre-deux-guerres, l'Office du Niger a acqui petit à petit le statut de facto d'un état dans l'État, dirigé par Émile Bélime.  En 1945, quand le projet a été finalement reconnu comme une échec sur le plan économique et humanitaire, les autorités coloniales ont essayé de corriger les erreurs les plus graves et lui ont accordé le nouveau statu de prototype pour d'autres projets d'assistance économique et technique aux régions sous-développées. En 1961, le Gouvernement du Mali, qui avait récemment accédé à l'indépendance, pensait en faire un projet pilote pour le développement agricole du pays. Sa réalisation détermine encore aujourd'hui la politique agricole du Mali. fr</dc:abstract><dc:abstract>The Office du Niger irrigation scheme, located on the Niger River in the Republic of Mali, originated in a grandiose but seriously flawed proposal devised in 1920 by a French colonial Public Works engineer named Emile Bélime.  Originaly conceived as a means of transforming the Niger Valley into a cotton belt, and later promoted as the heart of a French West African granary, the scheme never attained more than a tiny fraction of its presumed agricultural potential. Its construction and exploitation required the forced uprooting of tens of thousands of Africans. It absorbed a large portion of scarce colonial revenues until after the Second World War and generated no profits. During the inter-war period, the Office du Niger gradually acquired the de facto status of a state within the State, with Emile Bélime at its head.  When the scheme was finally recognized as an economic and humanitarian failure in 1945, colonial authorities endeavoured to eliminate its worst shortcomings and give it a new identity as a prototype of economic and technical assistance to an underdeveloped area. After 1961, Malian leaders felt that the scheme could be used as a pilot project for agricultural development in the new republlc, and the scheme's existence has dictated the course of Malian agricultural policy ever since.</dc:abstract><ual:supervisor>Myron Echenberg</ual:supervisor><ual:fedora3Handle>https://escholarship.mcgill.ca/downloads/1v53jz02s.PDF</ual:fedora3Handle><ual:fedora3Handle>https://escholarship.mcgill.ca/concern/theses/nz806066j</ual:fedora3Handle><dc:subject>France -- Colonies -- Africa -- Administration</dc:subject><dc:subject>Bélime, Emil</dc:subject><dc:subject>Mali -- Politics and government -- 20th century</dc:subject><dc:subject>Mali. Office du Niger -- History</dc:subject></rdf:Description></rdf:RDF>