{"last-modified-date":{"value":1465226976952},"name":{"created-date":{"value":1460761256816},"last-modified-date":{"value":1460761256816},"given-names":{"value":"Mohamed"},"family-name":{"value":"ElSalhy"},"credit-name":{"value":"ElSalhy M"},"source":null,"visibility":"PUBLIC","path":"0000-0002-7410-457X"},"other-names":{"last-modified-date":null,"other-name":[],"path":"/0000-0002-7410-457X/other-names"},"biography":{"created-date":{"value":1460761256818},"last-modified-date":{"value":1491241912053},"content":"","visibility":"PUBLIC","path":"/0000-0002-7410-457X/biography"},"researcher-urls":{"last-modified-date":null,"researcher-url":[],"path":"/0000-0002-7410-457X/researcher-urls"},"emails":{"last-modified-date":null,"email":[],"path":"/0000-0002-7410-457X/email"},"addresses":{"last-modified-date":{"value":1465226976952},"address":[{"created-date":{"value":1453660210778},"last-modified-date":{"value":1465226976952},"source":{"source-orcid":{"uri":"http://orcid.org/0000-0002-7410-457X","path":"0000-0002-7410-457X","host":"orcid.org"},"source-client-id":null,"source-name":{"value":"ElSalhy M"}},"country":{"value":"CA"},"visibility":"PUBLIC","path":"/0000-0002-7410-457X/address/305416","put-code":305416,"display-index":0}],"path":"/0000-0002-7410-457X/address"},"keywords":{"last-modified-date":{"value":1427136531065},"keyword":[{"created-date":{"value":1427136531030},"last-modified-date":{"value":1427136531030},"source":{"source-orcid":{"uri":"http://orcid.org/0000-0002-7410-457X","path":"0000-0002-7410-457X","host":"orcid.org"},"source-client-id":null,"source-name":{"value":"ElSalhy M"}},"content":"Caries","visibility":"PUBLIC","path":"/0000-0002-7410-457X/keywords/340943","put-code":340943,"display-index":0},{"created-date":{"value":1427136531035},"last-modified-date":{"value":1427136531035},"source":{"source-orcid":{"uri":"http://orcid.org/0000-0002-7410-457X","path":"0000-0002-7410-457X","host":"orcid.org"},"source-client-id":null,"source-name":{"value":"ElSalhy M"}},"content":"ICDAS","visibility":"PUBLIC","path":"/0000-0002-7410-457X/keywords/340944","put-code":340944,"display-index":0},{"created-date":{"value":1427136531040},"last-modified-date":{"value":1427136531040},"source":{"source-orcid":{"uri":"http://orcid.org/0000-0002-7410-457X","path":"0000-0002-7410-457X","host":"orcid.org"},"source-client-id":null,"source-name":{"value":"ElSalhy M"}},"content":"Xylitol","visibility":"PUBLIC","path":"/0000-0002-7410-457X/keywords/340945","put-code":340945,"display-index":0},{"created-date":{"value":1427136531048},"last-modified-date":{"value":1427136531048},"source":{"source-orcid":{"uri":"http://orcid.org/0000-0002-7410-457X","path":"0000-0002-7410-457X","host":"orcid.org"},"source-client-id":null,"source-name":{"value":"ElSalhy M"}},"content":"Oral Microbiology","visibility":"PUBLIC","path":"/0000-0002-7410-457X/keywords/340946","put-code":340946,"display-index":0},{"created-date":{"value":1427136531057},"last-modified-date":{"value":1427136531057},"source":{"source-orcid":{"uri":"http://orcid.org/0000-0002-7410-457X","path":"0000-0002-7410-457X","host":"orcid.org"},"source-client-id":null,"source-name":{"value":"ElSalhy M"}},"content":"OH Habits","visibility":"PUBLIC","path":"/0000-0002-7410-457X/keywords/340991","put-code":340991,"display-index":0},{"created-date":{"value":1427136531065},"last-modified-date":{"value":1427136531065},"source":{"source-orcid":{"uri":"http://orcid.org/0000-0002-7410-457X","path":"0000-0002-7410-457X","host":"orcid.org"},"source-client-id":null,"source-name":{"value":"ElSalhy M"}},"content":"Quality of Life","visibility":"PUBLIC","path":"/0000-0002-7410-457X/keywords/340992","put-code":340992,"display-index":0}],"path":"/0000-0002-7410-457X/keywords"},"external-identifiers":{"last-modified-date":null,"external-identifier":[],"path":"/0000-0002-7410-457X/external-identifiers"},"path":"/0000-0002-7410-457X/person"}