{"last-modified-date":{"value":1483722885947},"name":{"created-date":{"value":1460757669844},"last-modified-date":{"value":1460757669844},"given-names":{"value":"Joachim"},"family-name":{"value":"Beige"},"credit-name":{"value":""},"source":null,"visibility":"PUBLIC","path":"0000-0002-1907-825X"},"other-names":{"last-modified-date":null,"other-name":[],"path":"/0000-0002-1907-825X/other-names"},"biography":{"created-date":{"value":1460757669847},"last-modified-date":{"value":1460757669847},"content":"1994 - 2002 Residency and Transplantation Consultant, Dept. Nephrology, Free University Berlin\r\n2002 Visiting Scientist, Infection and Immunity (Dr. P. Halloran), University of Alberta, Edmonton, CN\r\n2002 - 03 Consultant, University Inselspital, Berne, Switzerland\r\nsince 2004 Department Medical Head, Nephrology and out-patient KfH Renal Unit, Hospital St. Georg, Leipzig, Germany\r\nAffiliated associated lectureship Martin-Luther University Halle/Wittenberg, Germany \r\n","visibility":"PUBLIC","path":"/0000-0002-1907-825X/biography"},"researcher-urls":{"last-modified-date":{"value":1483719960568},"researcher-url":[{"created-date":{"value":1483719960568},"last-modified-date":{"value":1483719960568},"source":{"source-orcid":{"uri":"http://orcid.org/0000-0002-1907-825X","path":"0000-0002-1907-825X","host":"orcid.org"},"source-client-id":null,"source-name":{"value":"Joachim Beige"}},"url-name":"Website of Leipzig Nephrology and outpatient Dept.","url":{"value":"http://www.nephro-leipzig.de"},"visibility":"PUBLIC","path":"/0000-0002-1907-825X/researcher-urls/987022","put-code":987022,"display-index":1}],"path":"/0000-0002-1907-825X/researcher-urls"},"emails":{"last-modified-date":null,"email":[],"path":"/0000-0002-1907-825X/email"},"addresses":{"last-modified-date":{"value":1465226976952},"address":[{"created-date":{"value":1453659659719},"last-modified-date":{"value":1465226976952},"source":{"source-orcid":{"uri":"http://orcid.org/0000-0002-1907-825X","path":"0000-0002-1907-825X","host":"orcid.org"},"source-client-id":null,"source-name":{"value":"Joachim Beige"}},"country":{"value":"DE"},"visibility":"PUBLIC","path":"/0000-0002-1907-825X/address/200941","put-code":200941,"display-index":0}],"path":"/0000-0002-1907-825X/address"},"keywords":{"last-modified-date":{"value":1395828273960},"keyword":[{"created-date":{"value":1395828273960},"last-modified-date":{"value":1395828273960},"source":{"source-orcid":{"uri":"http://orcid.org/0000-0002-1907-825X","path":"0000-0002-1907-825X","host":"orcid.org"},"source-client-id":null,"source-name":{"value":"Joachim Beige"}},"content":"nephrology, hypertension, renal transplantation","visibility":"PUBLIC","path":"/0000-0002-1907-825X/keywords/95470","put-code":95470,"display-index":0}],"path":"/0000-0002-1907-825X/keywords"},"external-identifiers":{"last-modified-date":{"value":1483722885947},"external-identifier":[{"created-date":{"value":1383303993718},"last-modified-date":{"value":1483722885947},"source":{"source-orcid":null,"source-client-id":{"uri":"http://orcid.org/client/0000-0002-5982-8983","path":"0000-0002-5982-8983","host":"orcid.org"},"source-name":{"value":"Scopus to ORCID"}},"external-id-type":"Scopus Author ID","external-id-value":"6701448507","external-id-url":{"value":"http://www.scopus.com/inward/authorDetails.url?authorID=6701448507&partnerID=MN8TOARS"},"external-id-relationship":"SELF","visibility":"PUBLIC","path":"/0000-0002-1907-825X/external-identifiers/167962","put-code":167962,"display-index":2},{"created-date":{"value":1483722875730},"last-modified-date":{"value":1483722885947},"source":{"source-orcid":null,"source-client-id":{"uri":"http://orcid.org/client/0000-0003-1377-5676","path":"0000-0003-1377-5676","host":"orcid.org"},"source-name":{"value":"ResearcherID"}},"external-id-type":"ResearcherID","external-id-value":"A-3446-2017","external-id-url":{"value":"http://www.researcherid.com/rid/A-3446-2017"},"external-id-relationship":"SELF","visibility":"PUBLIC","path":"/0000-0002-1907-825X/external-identifiers/619457","put-code":619457,"display-index":1}],"path":"/0000-0002-1907-825X/external-identifiers"},"path":"/0000-0002-1907-825X/person"}