{"last-modified-date":{"value":1486419448373},"name":{"created-date":{"value":1486160494458},"last-modified-date":{"value":1486160494458},"given-names":{"value":"Tim"},"family-name":{"value":"Spanos"},"credit-name":null,"source":null,"visibility":"PUBLIC","path":"0000-0003-2847-9597"},"other-names":{"last-modified-date":null,"other-name":[],"path":"/0000-0003-2847-9597/other-names"},"biography":null,"researcher-urls":{"last-modified-date":{"value":1486418926858},"researcher-url":[{"created-date":{"value":1486418926858},"last-modified-date":{"value":1486418926858},"source":{"source-orcid":{"uri":"http://orcid.org/0000-0003-2847-9597","path":"0000-0003-2847-9597","host":"orcid.org"},"source-client-id":null,"source-name":{"value":"Tim Spanos"}},"url-name":null,"url":{"value":"https://www.linkedin.com/in/tim-spanos-24025b14?trk=nav_responsive_tab_profile"},"visibility":"PUBLIC","path":"/0000-0003-2847-9597/researcher-urls/1043903","put-code":1043903,"display-index":1}],"path":"/0000-0003-2847-9597/researcher-urls"},"emails":{"last-modified-date":null,"email":[],"path":"/0000-0003-2847-9597/email"},"addresses":{"last-modified-date":{"value":1486418715830},"address":[{"created-date":{"value":1486418715830},"last-modified-date":{"value":1486418715830},"source":{"source-orcid":{"uri":"http://orcid.org/0000-0003-2847-9597","path":"0000-0003-2847-9597","host":"orcid.org"},"source-client-id":null,"source-name":{"value":"Tim Spanos"}},"country":{"value":"CA"},"visibility":"PUBLIC","path":"/0000-0003-2847-9597/address/626622","put-code":626622,"display-index":1}],"path":"/0000-0003-2847-9597/address"},"keywords":{"last-modified-date":{"value":1486419448373},"keyword":[{"created-date":{"value":1486419216529},"last-modified-date":{"value":1486419448373},"source":{"source-orcid":{"uri":"http://orcid.org/0000-0003-2847-9597","path":"0000-0003-2847-9597","host":"orcid.org"},"source-client-id":null,"source-name":{"value":"Tim Spanos"}},"content":"non-linear field theory","visibility":"PUBLIC","path":"/0000-0003-2847-9597/keywords/629625","put-code":629625,"display-index":2},{"created-date":{"value":1486419448367},"last-modified-date":{"value":1486419448367},"source":{"source-orcid":{"uri":"http://orcid.org/0000-0003-2847-9597","path":"0000-0003-2847-9597","host":"orcid.org"},"source-client-id":null,"source-name":{"value":"Tim Spanos"}},"content":"Lorentz invariant lattice gas","visibility":"PUBLIC","path":"/0000-0003-2847-9597/keywords/629630","put-code":629630,"display-index":1}],"path":"/0000-0003-2847-9597/keywords"},"external-identifiers":{"last-modified-date":null,"external-identifier":[],"path":"/0000-0003-2847-9597/external-identifiers"},"path":"/0000-0003-2847-9597/person"}