{"last-modified-date":{"value":1471301340514},"name":{"created-date":{"value":1471297417949},"last-modified-date":{"value":1471297417949},"given-names":{"value":"Kelly"},"family-name":{"value":"McPhee"},"credit-name":null,"source":null,"visibility":"PUBLIC","path":"0000-0001-8239-4805"},"other-names":{"last-modified-date":null,"other-name":[],"path":"/0000-0001-8239-4805/other-names"},"biography":null,"researcher-urls":{"last-modified-date":null,"researcher-url":[],"path":"/0000-0001-8239-4805/researcher-urls"},"emails":{"last-modified-date":null,"email":[],"path":"/0000-0001-8239-4805/email"},"addresses":{"last-modified-date":{"value":1471301262402},"address":[{"created-date":{"value":1471301262402},"last-modified-date":{"value":1471301262402},"source":{"source-orcid":{"uri":"http://orcid.org/0000-0001-8239-4805","path":"0000-0001-8239-4805","host":"orcid.org"},"source-client-id":null,"source-name":{"value":"Kelly McPhee"}},"country":{"value":"CA"},"visibility":"PUBLIC","path":"/0000-0001-8239-4805/address/515602","put-code":515602,"display-index":1}],"path":"/0000-0001-8239-4805/address"},"keywords":{"last-modified-date":{"value":1471301340514},"keyword":[{"created-date":{"value":1471301322315},"last-modified-date":{"value":1471301340514},"source":{"source-orcid":{"uri":"http://orcid.org/0000-0001-8239-4805","path":"0000-0001-8239-4805","host":"orcid.org"},"source-client-id":null,"source-name":{"value":"Kelly McPhee"}},"content":"Relaxometry","visibility":"PUBLIC","path":"/0000-0001-8239-4805/keywords/505256","put-code":505256,"display-index":9},{"created-date":{"value":1471301322323},"last-modified-date":{"value":1471301340514},"source":{"source-orcid":{"uri":"http://orcid.org/0000-0001-8239-4805","path":"0000-0001-8239-4805","host":"orcid.org"},"source-client-id":null,"source-name":{"value":"Kelly McPhee"}},"content":"Transverse relaxation","visibility":"PUBLIC","path":"/0000-0001-8239-4805/keywords/505257","put-code":505257,"display-index":8},{"created-date":{"value":1471301322325},"last-modified-date":{"value":1471301340514},"source":{"source-orcid":{"uri":"http://orcid.org/0000-0001-8239-4805","path":"0000-0001-8239-4805","host":"orcid.org"},"source-client-id":null,"source-name":{"value":"Kelly McPhee"}},"content":"indirect and stimulated echo compensation","visibility":"PUBLIC","path":"/0000-0001-8239-4805/keywords/505258","put-code":505258,"display-index":7},{"created-date":{"value":1471301322327},"last-modified-date":{"value":1471301340514},"source":{"source-orcid":{"uri":"http://orcid.org/0000-0001-8239-4805","path":"0000-0001-8239-4805","host":"orcid.org"},"source-client-id":null,"source-name":{"value":"Kelly McPhee"}},"content":"ISEC","visibility":"PUBLIC","path":"/0000-0001-8239-4805/keywords/505259","put-code":505259,"display-index":6},{"created-date":{"value":1471301322328},"last-modified-date":{"value":1471301340514},"source":{"source-orcid":{"uri":"http://orcid.org/0000-0001-8239-4805","path":"0000-0001-8239-4805","host":"orcid.org"},"source-client-id":null,"source-name":{"value":"Kelly McPhee"}},"content":"T2","visibility":"PUBLIC","path":"/0000-0001-8239-4805/keywords/505260","put-code":505260,"display-index":5},{"created-date":{"value":1471301322330},"last-modified-date":{"value":1471301340514},"source":{"source-orcid":{"uri":"http://orcid.org/0000-0001-8239-4805","path":"0000-0001-8239-4805","host":"orcid.org"},"source-client-id":null,"source-name":{"value":"Kelly McPhee"}},"content":"T1","visibility":"PUBLIC","path":"/0000-0001-8239-4805/keywords/505261","put-code":505261,"display-index":4},{"created-date":{"value":1471301322331},"last-modified-date":{"value":1471301340514},"source":{"source-orcid":{"uri":"http://orcid.org/0000-0001-8239-4805","path":"0000-0001-8239-4805","host":"orcid.org"},"source-client-id":null,"source-name":{"value":"Kelly McPhee"}},"content":"Magnetic Resonance Imaging","visibility":"PUBLIC","path":"/0000-0001-8239-4805/keywords/505262","put-code":505262,"display-index":3},{"created-date":{"value":1471301340504},"last-modified-date":{"value":1471301340504},"source":{"source-orcid":{"uri":"http://orcid.org/0000-0001-8239-4805","path":"0000-0001-8239-4805","host":"orcid.org"},"source-client-id":null,"source-name":{"value":"Kelly McPhee"}},"content":"Medical Imaging","visibility":"PUBLIC","path":"/0000-0001-8239-4805/keywords/505263","put-code":505263,"display-index":2},{"created-date":{"value":1471301340511},"last-modified-date":{"value":1471301340511},"source":{"source-orcid":{"uri":"http://orcid.org/0000-0001-8239-4805","path":"0000-0001-8239-4805","host":"orcid.org"},"source-client-id":null,"source-name":{"value":"Kelly McPhee"}},"content":"Medical Physics","visibility":"PUBLIC","path":"/0000-0001-8239-4805/keywords/505264","put-code":505264,"display-index":1}],"path":"/0000-0001-8239-4805/keywords"},"external-identifiers":{"last-modified-date":{"value":1471298746890},"external-identifier":[{"created-date":{"value":1471297957161},"last-modified-date":{"value":1471298746890},"source":{"source-orcid":null,"source-client-id":{"uri":"http://orcid.org/client/0000-0002-5982-8983","path":"0000-0002-5982-8983","host":"orcid.org"},"source-name":{"value":"Scopus to ORCID"}},"external-id-type":"Scopus Author ID","external-id-value":"57190180431","external-id-url":{"value":"http://www.scopus.com/inward/authorDetails.url?authorID=57190180431&partnerID=MN8TOARS"},"external-id-relationship":"SELF","visibility":"PUBLIC","path":"/0000-0001-8239-4805/external-identifiers/528732","put-code":528732,"display-index":1},{"created-date":{"value":1471298746803},"last-modified-date":{"value":1471298746803},"source":{"source-orcid":null,"source-client-id":{"uri":"http://orcid.org/client/0000-0002-5982-8983","path":"0000-0002-5982-8983","host":"orcid.org"},"source-name":{"value":"Scopus to ORCID"}},"external-id-type":"Scopus Author ID","external-id-value":"39261833100","external-id-url":{"value":"http://www.scopus.com/inward/authorDetails.url?authorID=39261833100&partnerID=MN8TOARS"},"external-id-relationship":"SELF","visibility":"PUBLIC","path":"/0000-0001-8239-4805/external-identifiers/528735","put-code":528735,"display-index":0}],"path":"/0000-0001-8239-4805/external-identifiers"},"path":"/0000-0001-8239-4805/person"}