{"last-modified-date":{"value":1365307809338},"name":{"created-date":{"value":1460763519240},"last-modified-date":{"value":1460763519240},"given-names":{"value":"Chun "},"family-name":{"value":"Yang"},"credit-name":null,"source":null,"visibility":"PUBLIC","path":"0000-0003-1191-7642"},"other-names":{"last-modified-date":null,"other-name":[],"path":"/0000-0003-1191-7642/other-names"},"biography":null,"researcher-urls":{"last-modified-date":null,"researcher-url":[],"path":"/0000-0003-1191-7642/researcher-urls"},"emails":{"last-modified-date":null,"email":[],"path":"/0000-0003-1191-7642/email"},"addresses":{"last-modified-date":null,"address":[],"path":"/0000-0003-1191-7642/address"},"keywords":{"last-modified-date":null,"keyword":[],"path":"/0000-0003-1191-7642/keywords"},"external-identifiers":{"last-modified-date":{"value":1365307809338},"external-identifier":[{"created-date":{"value":1365307809338},"last-modified-date":{"value":1365307809338},"source":{"source-orcid":{"uri":"http://orcid.org/0000-0001-7707-4137","path":"0000-0001-7707-4137","host":"orcid.org"},"source-client-id":null,"source-name":{"value":"Clarivate Analytics"}},"external-id-type":"ResearcherID","external-id-value":"A-7467-2008","external-id-url":{"value":"http://www.researcherid.com/rid/A-7467-2008"},"external-id-relationship":"SELF","visibility":"PUBLIC","path":"/0000-0003-1191-7642/external-identifiers/15994","put-code":15994,"display-index":0}],"path":"/0000-0003-1191-7642/external-identifiers"},"path":"/0000-0003-1191-7642/person"}