<?xml version="1.0" encoding="UTF-8"?>
<record xmlns="http://www.loc.gov/MARC21/slim">
   <leader>02239cas a2200541 a 4500</leader>
   <controlfield tag="001">1743637</controlfield>
   <controlfield tag="008">960227c19959999abcfr p      s0     eng d</controlfield>
   <datafield tag="022" ind1=" " ind2=" ">
      <subfield code="a">1709-4186</subfield>
   </datafield>
   <datafield tag="035" ind1=" " ind2=" ">
      <subfield code="a">ocn462099763</subfield>
   </datafield>
   <datafield tag="040" ind1=" " ind2=" ">
      <subfield code="a">AEU</subfield>
      <subfield code="b">eng</subfield>
   </datafield>
   <datafield tag="043" ind1=" " ind2=" ">
      <subfield code="a">n-cn-ab</subfield>
   </datafield>
   <datafield tag="055" ind1=" " ind2="3">
      <subfield code="a">QE 186</subfield>
      <subfield code="b">R63</subfield>
   </datafield>
   <datafield tag="090" ind1=" " ind2=" ">
      <subfield code="a">QE 186 R63</subfield>
      <subfield code="b">AEU</subfield>
   </datafield>
   <datafield tag="090" ind1=" " ind2=" ">
      <subfield code="a">SHELVED BY TITLE</subfield>
      <subfield code="b">AEE</subfield>
   </datafield>
   <datafield tag="240" ind1="0" ind2="0">
      <subfield code="a">Rock chips :</subfield>
      <subfield code="b">a newsletter published by the Alberta Geological Survey for the geoscience community of Alberta.</subfield>
   </datafield>
   <datafield tag="245" ind1="0" ind2="0">
      <subfield code="a">Rock Chips : A Newsletter Published by the Alberta Geological Survey for the Geoscience Community of Alberta 2002</subfield>
      <subfield code="b">a newsletter published by the Alberta Geological Survey for the geoscience community of Alberta.</subfield>
   </datafield>
   <datafield tag="260" ind1=" " ind2=" ">
      <subfield code="a">Edmonton :</subfield>
      <subfield code="b">Alberta Energy,</subfield>
      <subfield code="c">[1995-2012]</subfield>
   </datafield>
   <datafield tag="300" ind1=" " ind2=" ">
      <subfield code="a">v. :</subfield>
      <subfield code="b">ill. ;</subfield>
      <subfield code="c">28 cm.</subfield>
   </datafield>
   <datafield tag="310" ind1=" " ind2=" ">
      <subfield code="a">Semiannual</subfield>
   </datafield>
   <datafield tag="336" ind1=" " ind2=" ">
      <subfield code="a">text</subfield>
      <subfield code="b">txt</subfield>
      <subfield code="2">rdacontent</subfield>
   </datafield>
   <datafield tag="337" ind1=" " ind2=" ">
      <subfield code="a">unmediated</subfield>
      <subfield code="b">n</subfield>
      <subfield code="2">rdamedia</subfield>
   </datafield>
   <datafield tag="338" ind1=" " ind2=" ">
      <subfield code="a">volume</subfield>
      <subfield code="b">nc</subfield>
      <subfield code="2">rdacarrier</subfield>
   </datafield>
   <datafield tag="362" ind1="0" ind2=" ">
      <subfield code="a">Spring/summer 1995-Spring 2012.</subfield>
   </datafield>
   <datafield tag="500" ind1=" " ind2=" ">
      <subfield code="a">Title from caption.</subfield>
   </datafield>
   <datafield tag="596" ind1=" " ind2=" ">
      <subfield code="a">2 48</subfield>
   </datafield>
   <datafield tag="599" ind1=" " ind2=" ">
      <subfield code="a">33</subfield>
      <subfield code="b">FALL/WIN 2005 FALL/WIN 2005;</subfield>
   </datafield>
   <datafield tag="650" ind1=" " ind2="0">
      <subfield code="a">Geology</subfield>
      <subfield code="z">Alberta</subfield>
      <subfield code="v">Periodicals.</subfield>
   </datafield>
   <datafield tag="710" ind1="2" ind2=" ">
      <subfield code="a">Alberta Geological Survey.</subfield>
   </datafield>
   <datafield tag="710" ind1="1" ind2=" ">
      <subfield code="a">Alberta.</subfield>
      <subfield code="b">Alberta Energy.</subfield>
   </datafield>
   <datafield tag="940" ind1=" " ind2=" ">
      <subfield code="a">NO EJOURNAL HOLDINGS</subfield>
   </datafield>
   <datafield tag="926" ind1=" " ind2=" ">
      <subfield code="a">AGL_CAP</subfield>
      <subfield code="b">PERIODICAL</subfield>
      <subfield code="c">SHELVED BY TITLE</subfield>
      <subfield code="d">PERIODICAL</subfield>
      <subfield code="f">1</subfield>
   </datafield>
   <datafield tag="926" ind1=" " ind2=" ">
      <subfield code="a">UASCITECH</subfield>
      <subfield code="b">ON_SHELF</subfield>
      <subfield code="c">QE 186 R63 1995: spring/summer</subfield>
      <subfield code="d">PERIODICAL</subfield>
      <subfield code="f">1</subfield>
   </datafield>
   <datafield tag="926" ind1=" " ind2=" ">
      <subfield code="a">UASCITECH</subfield>
      <subfield code="b">ON_SHELF</subfield>
      <subfield code="c">QE 186 R63 1996: fall/winter</subfield>
      <subfield code="d">PERIODICAL</subfield>
      <subfield code="f">1</subfield>
   </datafield>
   <datafield tag="926" ind1=" " ind2=" ">
      <subfield code="a">UASCITECH</subfield>
      <subfield code="b">ON_SHELF</subfield>
      <subfield code="c">QE 186 R63 1998/1999: winter</subfield>
      <subfield code="d">PERIODICAL</subfield>
      <subfield code="f">1</subfield>
   </datafield>
   <datafield tag="926" ind1=" " ind2=" ">
      <subfield code="a">UASCITECH</subfield>
      <subfield code="b">ON_SHELF</subfield>
      <subfield code="c">QE 186 R63 1998: spring</subfield>
      <subfield code="d">PERIODICAL</subfield>
      <subfield code="f">1</subfield>
   </datafield>
   <datafield tag="926" ind1=" " ind2=" ">
      <subfield code="a">UASCITECH</subfield>
      <subfield code="b">ON_SHELF</subfield>
      <subfield code="c">QE 186 R63 1999: autumn</subfield>
      <subfield code="d">PERIODICAL</subfield>
      <subfield code="f">1</subfield>
   </datafield>
   <datafield tag="926" ind1=" " ind2=" ">
      <subfield code="a">UASCITECH</subfield>
      <subfield code="b">ON_SHELF</subfield>
      <subfield code="c">QE 186 R63 2001: fall/winter</subfield>
      <subfield code="d">PERIODICAL</subfield>
      <subfield code="f">1</subfield>
   </datafield>
   <datafield tag="926" ind1=" " ind2=" ">
      <subfield code="a">UASCITECH</subfield>
      <subfield code="b">ON_SHELF</subfield>
      <subfield code="c">QE 186 R63 2002: fall/winter</subfield>
      <subfield code="d">PERIODICAL</subfield>
      <subfield code="f">1</subfield>
   </datafield>
   <datafield tag="926" ind1=" " ind2=" ">
      <subfield code="a">UASCITECH</subfield>
      <subfield code="b">ON_SHELF</subfield>
      <subfield code="c">QE 186 R63 2003-2004</subfield>
      <subfield code="d">PERIODICAL</subfield>
      <subfield code="f">1</subfield>
   </datafield>
   <datafield tag="926" ind1=" " ind2=" ">
      <subfield code="a">UASCITECH</subfield>
      <subfield code="b">ON_SHELF</subfield>
      <subfield code="c">QE 186 R63 2005: fall/winter</subfield>
      <subfield code="d">PERIODICAL</subfield>
      <subfield code="f">1</subfield>
   </datafield>
   <datafield tag="926" ind1=" " ind2=" ">
      <subfield code="a">UASCITECH</subfield>
      <subfield code="b">ON_SHELF</subfield>
      <subfield code="c">QE 186 R63 2005: spring</subfield>
      <subfield code="d">PERIODICAL</subfield>
      <subfield code="f">1</subfield>
   </datafield>
   <datafield tag="926" ind1=" " ind2=" ">
      <subfield code="a">UASCITECH</subfield>
      <subfield code="b">ON_SHELF</subfield>
      <subfield code="c">QE 186 R63 2006</subfield>
      <subfield code="d">PERIODICAL</subfield>
      <subfield code="f">1</subfield>
   </datafield>
   <datafield tag="926" ind1=" " ind2=" ">
      <subfield code="a">UASCITECH</subfield>
      <subfield code="b">ON_SHELF</subfield>
      <subfield code="c">QE 186 R63 2007: spring</subfield>
      <subfield code="d">PERIODICAL</subfield>
      <subfield code="f">1</subfield>
   </datafield>
   <datafield tag="927" ind1=" " ind2=" ">
      <subfield code="a">AGL_CAP</subfield>
   </datafield>
   <datafield tag="927" ind1=" " ind2=" ">
      <subfield code="b">Location</subfield>
      <subfield code="c">PERIODICAL-- SHELVED BY TITLE</subfield>
   </datafield>
   <datafield tag="927" ind1=" " ind2=" ">
      <subfield code="b">Library has</subfield>
      <subfield code="c">1991-2012 (Spr)</subfield>
   </datafield>
   <datafield tag="927" ind1=" " ind2=" ">
      <subfield code="a">UASCITECH</subfield>
   </datafield>
   <datafield tag="927" ind1=" " ind2=" ">
      <subfield code="b">Location</subfield>
      <subfield code="c">ON_SHELF-- QE 186 R63</subfield>
   </datafield>
   <datafield tag="927" ind1=" " ind2=" ">
      <subfield code="b">Library has</subfield>
      <subfield code="c">1995-1996,1998-2007</subfield>
   </datafield>
</record>
