<?xml version="1.0" encoding="UTF-8"?>
<rdf:Description xmlns:rdf="http://www.w3.org/1999/02/22-rdf-syntax-ns#"
                 xmlns:dc="http://purl.org/dc/elements/1.1/">
   <dc:title>Science 14 1991</dc:title>
   <dc:creator>
      Alberta.
      Distance Learning.
   </dc:creator>
   <dc:creator>
      Alberta.
      Alberta Education.
   </dc:creator>
   <dc:type>text</dc:type>
   <dc:language>eng</dc:language>
   <dc:description>Module 1. Science &amp; technology--Module 2. Technology in action--Module 3. The balance of life--Module 4. Technology for life--Module 5. Mixing and measuring--Module 6. Household products and reactions--Module 7. Environmental explorations--Module 8. Technology and the environment -- Learning facilitator's manual: modules 1-8.</dc:description>
   <dc:description>Approved for use in Alberta schools.</dc:description>
   <dc:description>38</dc:description>
   <dc:subject>Science</dc:subject>
   <dc:identifier>URN:ISBN:no isbn (modules 1-8) (learning facilitator's manual)</dc:identifier>
   <dc:identifier>URN:ISBN:0774102977 (module 1)</dc:identifier>
   <dc:identifier>URN:ISBN:9780774102971</dc:identifier>
   <dc:identifier>URN:ISBN:0774104716 (module 8) (learning faciltator's manual)</dc:identifier>
   <dc:identifier>URN:ISBN:9780774104715</dc:identifier>
   <dc:identifier>URN:ISBN:0774104589 (module 7) (learning facilitator's manual)</dc:identifier>
   <dc:identifier>URN:ISBN:9780774104586</dc:identifier>
   <dc:identifier>URN:ISBN:0774104554 (module 6) (learning facilitator's manual)</dc:identifier>
   <dc:identifier>URN:ISBN:9780774104555</dc:identifier>
   <dc:identifier>URN:ISBN:0774103949 (module 5) (learning facilitator's manual)</dc:identifier>
   <dc:identifier>URN:ISBN:9780774103947</dc:identifier>
   <dc:identifier>URN:ISBN:0774104430 (module 4) (learning facilitator's manual)</dc:identifier>
   <dc:identifier>URN:ISBN:9780774104432</dc:identifier>
   <dc:identifier>URN:ISBN:0774103728 (module 3) (learning facilitator's manual)</dc:identifier>
   <dc:identifier>URN:ISBN:9780774103725</dc:identifier>
   <dc:identifier>URN:ISBN:0774103426 (module 2) (learning facilitator's manual)</dc:identifier>
   <dc:identifier>URN:ISBN:9780774103428</dc:identifier>
   <dc:identifier>URN:ISBN:0774102993 (module 1) (learning facilitator's manual)</dc:identifier>
   <dc:identifier>URN:ISBN:9780774102995</dc:identifier>
   <dc:identifier>URN:ISBN:0774104414 (module 4)</dc:identifier>
   <dc:identifier>URN:ISBN:9780774104418</dc:identifier>
   <dc:identifier>URN:ISBN:0774103698 (module 3)</dc:identifier>
   <dc:identifier>URN:ISBN:9780774103695</dc:identifier>
   <dc:identifier>URN:ISBN:0774103396 (module 2)</dc:identifier>
   <dc:identifier>URN:ISBN:9780774103398</dc:identifier>
   <dc:identifier>URN:ISBN:0774103922 (module 5)</dc:identifier>
   <dc:identifier>URN:ISBN:9780774103923</dc:identifier>
   <dc:identifier>URN:ISBN:0774103752 (module 6)</dc:identifier>
   <dc:identifier>URN:ISBN:9780774103756</dc:identifier>
   <dc:identifier>URN:ISBN:0774104562 (module 7)</dc:identifier>
   <dc:identifier>URN:ISBN:9780774104562</dc:identifier>
   <dc:identifier>URN:ISBN:0774104694 (module 8)</dc:identifier>
   <dc:identifier>URN:ISBN:9780774104692</dc:identifier>
</rdf:Description>
