<record><leader>02656cam a2200493 i 45 0</leader><controlfield tag="001">6801968</controlfield><controlfield tag="003">OCoLC</controlfield><controlfield tag="005">20150209164026.0</controlfield><controlfield tag="006">m                 </controlfield><controlfield tag="007">cr*|||||||||||</controlfield><controlfield tag="008">141110s2015    enk           000 0 eng  </controlfield><datafield ind1=" " ind2=" " tag="010"><subfield code="a">  2014031652</subfield></datafield><datafield ind1=" " ind2=" " tag="015"><subfield code="a">GBB4E9886</subfield><subfield code="2">bnb</subfield></datafield><datafield ind1="7" ind2=" " tag="016"><subfield code="a">016983549</subfield><subfield code="2">Uk</subfield></datafield><datafield ind1=" " ind2=" " tag="020"><subfield code="a">9781107279568 (ebook)</subfield></datafield><datafield ind1=" " ind2=" " tag="020"><subfield code="a">9781107050501 (hardback)</subfield></datafield><datafield ind1=" " ind2=" " tag="020"><subfield code="a">1107050502 (hardback)</subfield></datafield><datafield ind1=" " ind2=" " tag="020"><subfield code="a">9781107642348 (paperback)</subfield></datafield><datafield ind1=" " ind2=" " tag="020"><subfield code="a">1107642345 (paperback)</subfield></datafield><datafield ind1=" " ind2=" " tag="035"><subfield code="a">ocn903198924</subfield></datafield><datafield ind1=" " ind2=" " tag="040"><subfield code="a">DLC</subfield><subfield code="b">eng</subfield><subfield code="e">rda</subfield><subfield code="c">DLC</subfield><subfield code="d">OCLCO</subfield><subfield code="d">UKMGB</subfield><subfield code="d">BTCTA</subfield><subfield code="d">CDX</subfield><subfield code="d">AEU</subfield></datafield><datafield ind1=" " ind2=" " tag="042"><subfield code="a">pcc</subfield></datafield><datafield ind1=" " ind2=" " tag="043"><subfield code="a">e-uk---</subfield></datafield><datafield ind1="0" ind2="0" tag="050"><subfield code="a">JN1361b.A55 2015</subfield></datafield><datafield ind1="0" ind2="0" tag="082"><subfield code="a">172.0941</subfield><subfield code="2">23</subfield></datafield><datafield ind1=" " ind2=" " tag="084"><subfield code="a">POL040000</subfield><subfield code="2">bisacsh</subfield></datafield><datafield ind1=" " ind2=" " tag="090"><subfield code="a">Internet Access</subfield><subfield code="b">AEU</subfield></datafield><datafield ind1="1" ind2=" " tag="100"><subfield code="a">Allen, Nicholas.</subfield></datafield><datafield ind1="1" ind2="0" tag="245"><subfield code="a">Ethics and integrity in British politics :</subfield><subfield code="b">how citizens judge their politicians' conduct and why it matters /</subfield><subfield code="c">Nicholas Allen, Sarah Birch.</subfield></datafield><datafield ind1=" " ind2="1" tag="264"><subfield code="a">Cambridge ;</subfield><subfield code="a">New York :</subfield><subfield code="b">Cambridge University Press,</subfield><subfield code="c">2015.</subfield></datafield><datafield ind1=" " ind2=" " tag="300"><subfield code="a">1 online resource.</subfield></datafield><datafield ind1=" " ind2=" " tag="336"><subfield code="a">text</subfield><subfield code="2">rdacontent</subfield></datafield><datafield ind1=" " ind2=" " tag="337"><subfield code="a">computer</subfield><subfield code="2">rdamedia</subfield></datafield><datafield ind1=" " ind2=" " tag="338"><subfield code="a">online resource</subfield><subfield code="2">rdacarrier</subfield></datafield><datafield ind1=" " ind2=" " tag="506"><subfield code="a">Access restricted to authorized users and institutions.</subfield></datafield><datafield ind1=" " ind2=" " tag="520"><subfield code="a">"Public perceptions of political ethics are at the heart of current political debate. Drawing on original data, this book is the first general account of popular understandings of political ethics in contemporary British politics. It offers new insights into how citizens understand political ethics and integrity and how they form judgments of their leaders. By locating these insights against the backdrop of contemporary British political ethics, the book shows how current institutional preoccupations with standards of conduct all too often miss the mark. While the use of official resources is the primary focus of much regulation, politicians' consistency, frankness and sincerity, which citizens tend to see in terms of right and wrong, are treated as 'normal politics'. The authors suggest that new approaches may need to be adopted if public confidence in politicians' integrity is to be restored"--</subfield><subfield code="c">Provided by publisher.</subfield></datafield><datafield ind1=" " ind2=" " tag="596"><subfield code="a">44</subfield></datafield><datafield ind1=" " ind2="0" tag="650"><subfield code="a">Political corruption</subfield><subfield code="z">Great Britain.</subfield></datafield><datafield ind1=" " ind2="0" tag="650"><subfield code="a">Political ethics</subfield><subfield code="z">Great Britain.</subfield></datafield><datafield ind1=" " ind2="0" tag="650"><subfield code="a">Politicians</subfield><subfield code="z">Great Britain.</subfield></datafield><datafield ind1=" " ind2="0" tag="651"><subfield code="a">Great Britain</subfield><subfield code="x">Politics and government.</subfield></datafield><datafield ind1="1" ind2=" " tag="700"><subfield code="a">Birch, Sarah.</subfield></datafield><datafield ind1="4" ind2="0" tag="856"><subfield code="3">University of Alberta Access</subfield><subfield code="u">http://dx.doi.org/10.1017/CBO9781107279568</subfield></datafield><datafield ind1=" " ind2=" " tag="926"><subfield code="a">Internet Access</subfield><subfield code="w">LC</subfield><subfield code="c">1</subfield><subfield code="i">6801968-1001</subfield><subfield code="l">INTERNET</subfield><subfield code="m">UAINTERNET</subfield><subfield code="r">Y</subfield><subfield code="s">Y</subfield><subfield code="t">E-RESOURCE</subfield><subfield code="u">2/9/2015</subfield><subfield code="x">E-BOOK</subfield><subfield code="z">CBO</subfield></datafield></record>